<?xml version="1.0" encoding="utf-8" ?>
<dwsync>
<file name="ceviche-gambas.jpg" server="ftp.fatcow.com" local="132839954857218994" remote="132840603000000000" Dst="0" />
<file name="biking-cusco.jpg" server="ftp.fatcow.com" local="132839955098672549" remote="132840603000000000" Dst="0" />
<file name="chincheros.jpg" server="ftp.fatcow.com" local="132839954699361744" remote="132840603000000000" Dst="0" />
<file name="cusco-01.JPG" server="ftp.fatcow.com" local="132839954330802362" remote="132840603000000000" Dst="0" />
<file name="destino-per.JPG" server="ftp.fatcow.com" local="132839954458159593" remote="132840603000000000" Dst="0" />
<file name="llama-peru.JPG" server="ftp.fatcow.com" local="132839954158231611" remote="132840603000000000" Dst="0" />
<file name="llamas.jpg" server="ftp.fatcow.com" local="132839953997815903" remote="132840603000000000" Dst="0" />
<file name="Machupicchu.jpg" server="ftp.fatcow.com" local="132839953800984003" remote="132840603000000000" Dst="0" />
<file name="Machupicchu_AET.jpg" server="ftp.fatcow.com" local="132839953525625845" remote="132840603000000000" Dst="0" />
<file name="pachamama-ceremony-andean-exclusive.jpg" server="ftp.fatcow.com" local="132839998793581989" remote="132840603000000000" Dst="0" />
<file name="Peru-Arenero-y-Sandboarding-en-Huacachina.JPG" server="ftp.fatcow.com" local="132839951655300029" remote="132840603000000000" Dst="0" />
<file name="puno-peru.JPG" server="ftp.fatcow.com" local="132839951463868462" remote="132840603000000000" Dst="0" />
<file name="wedding-in-perú-andean.jfif" server="ftp.fatcow.com" local="132839949457242185" remote="132840603000000000" Dst="0" />
<file name="vacaciones-familiares-peru.jpg" server="ftp.fatcow.com" local="132839950701186048" remote="132840603000000000" Dst="0" />
<file name="urubamba-market.png" server="ftp.fatcow.com" local="132839951216415849" remote="132840603000000000" Dst="0" />
<file name="biking-cusco.jpg" server="157.245.81.162" local="132839955098672549" remote="132966321000000000" Dst="0" />
<file name="ceviche-gambas.jpg" server="157.245.81.162" local="132839954857218994" remote="132966321000000000" Dst="0" />
<file name="chincheros.jpg" server="157.245.81.162" local="132839954699361744" remote="132966321000000000" Dst="0" />
<file name="cusco-01.JPG" server="157.245.81.162" local="132839954330802362" remote="132966321000000000" Dst="0" />
<file name="destino-per.JPG" server="157.245.81.162" local="132839954458159593" remote="132966321000000000" Dst="0" />
<file name="llama-peru.JPG" server="157.245.81.162" local="132839954158231611" remote="132966321000000000" Dst="0" />
<file name="llamas.jpg" server="157.245.81.162" local="132839953997815903" remote="132966321000000000" Dst="0" />
<file name="Machupicchu.jpg" server="157.245.81.162" local="132839953800984003" remote="132998919000000000" Dst="0" />
<file name="Machupicchu_AET.jpg" server="157.245.81.162" local="132839953525625845" remote="132966321000000000" Dst="0" />
<file name="mono-amazonas.jpg" server="157.245.81.162" local="132858026730538647" remote="132966321000000000" Dst="0" />
<file name="pachamama-ceremony-andean-exclusive.jpg" server="157.245.81.162" local="132839998793581989" remote="132966321000000000" Dst="0" />
<file name="Peru-Arenero-y-Sandboarding-en-Huacachina.JPG" server="157.245.81.162" local="132839951655300029" remote="132966321000000000" Dst="0" />
<file name="puno-peru.JPG" server="157.245.81.162" local="132839951463868462" remote="132966321000000000" Dst="0" />
<file name="wedding-in-perú-andean.jfif" server="157.245.81.162" local="132839949457242185" remote="132966321000000000" Dst="0" />
<file name="urubamba-market.png" server="157.245.81.162" local="132839951216415849" remote="132966321000000000" Dst="0" />
<file name="vacaciones-familiares-peru.jpg" server="157.245.81.162" local="132919460537161788" remote="132966321000000000" Dst="0" />
<file name="vacaciones-familiares-peru.webp" server="157.245.81.162" local="132938329862222335" remote="132938509800000000" Dst="0" />
<file name="Arenero-y-Sandboarding-en-Huacachina.webp" server="157.245.81.162" local="132919396024540882" remote="132962561400000000" Dst="0" />
<file name="arequipa-peru.JPG" server="157.245.81.162" local="132839955535052768" remote="132962561400000000" Dst="0" />
<file name="arequipa-peru.webp" server="157.245.81.162" local="132919395497790546" remote="132962561400000000" Dst="0" />
<file name="biking-cusco.webp" server="157.245.81.162" local="132919395600321724" remote="132962561400000000" Dst="0" />
<file name="ceviche-gambas.webp" server="157.245.81.162" local="132919395685753336" remote="132962562000000000" Dst="0" />
<file name="chincheros.webp" server="157.245.81.162" local="132919395654074667" remote="132962562000000000" Dst="0" />
<file name="cusco-01.webp" server="157.245.81.162" local="132919395570903837" remote="132962562600000000" Dst="0" />
<file name="destino-per.webp" server="157.245.81.162" local="132919395630281538" remote="132962562600000000" Dst="0" />
<file name="llama-peru.webp" server="157.245.81.162" local="132919395542571112" remote="132962563200000000" Dst="0" />
<file name="llamas.webp" server="157.245.81.162" local="132919396000164314" remote="132962563200000000" Dst="0" />
<file name="Machupicchu.webp" server="157.245.81.162" local="132919396052215618" remote="132962563800000000" Dst="0" />
<file name="mono-amazonas.webp" server="157.245.81.162" local="132919396079848059" remote="132962563800000000" Dst="0" />
<file name="pachamama-ceremony-andean-exclusive.webp" server="157.245.81.162" local="132919442267582800" remote="132962564400000000" Dst="0" />
<file name="Peru-Arenero-y-Sandboarding-en-Huacachina.webp" server="157.245.81.162" local="132919442327895864" remote="132962564400000000" Dst="0" />
<file name="puno-peru.webp" server="157.245.81.162" local="132919442349415021" remote="132962565000000000" Dst="0" />
<file name="urubamba-market.webp" server="157.245.81.162" local="132919442368355959" remote="132962565000000000" Dst="0" />
<file name="wedding-in-perú-andean.webp" server="157.245.81.162" local="132919442404946795" remote="132962565600000000" Dst="0" />
</dwsync>