<?xml version="1.0" encoding="utf-8" ?>
<dwsync>
<file name="CHINCHERO.jpg" server="ftp.fatcow.com" local="132819368780000000" remote="132840603600000000" Dst="0" />
<file name="Humantay.jpg" server="ftp.fatcow.com" local="132819368780000000" remote="132840603600000000" Dst="0" />
<file name="blog-hiking-peru.jpg" server="ftp.fatcow.com" local="132819368800000000" remote="132840603600000000" Dst="0" />
<file name="book AET.jpg" server="ftp.fatcow.com" local="132819368820000000" remote="132840603600000000" Dst="0" />
<file name="book-your-destination-to-peru.jpg" server="ftp.fatcow.com" local="132819368820000000" remote="132840603600000000" Dst="0" />
<file name="Machu-Picchu-exclusive.jpg" server="ftp.fatcow.com" local="132819368840000000" remote="132840604200000000" Dst="0" />
<file name="chincheros.jpg" server="ftp.fatcow.com" local="132819368840000000" remote="132840603600000000" Dst="0" />
<file name="cusco-de-noche.jpg" server="ftp.fatcow.com" local="132819368840000000" remote="132840603600000000" Dst="0" />
<file name="condor.png" server="ftp.fatcow.com" local="132819368840000000" remote="132840603600000000" Dst="0" />
<file name="faqs.jpg" server="ftp.fatcow.com" local="132819368860000000" remote="132840603600000000" Dst="0" />
<file name="ingles.png" server="ftp.fatcow.com" local="132819368920000000" remote="132840604200000000" Dst="0" />
<file name="llama2.jpg" server="ftp.fatcow.com" local="132819368940000000" remote="132840604200000000" Dst="0" />
<file name="llamas.jpg" server="ftp.fatcow.com" local="132819368940000000" remote="132840604200000000" Dst="0" />
<file name="logodjm.png" server="ftp.fatcow.com" local="132820114340000000" remote="132840604200000000" Dst="0" />
<file name="logoico.png" server="ftp.fatcow.com" local="132819368940000000" remote="132840604200000000" Dst="0" />
<file name="opiniones.png" server="ftp.fatcow.com" local="132819368960000000" remote="132840604200000000" Dst="0" />
<file name="otorongo-jaguars.jpg" server="ftp.fatcow.com" local="132819368980000000" remote="132840604200000000" Dst="0" />
<file name="machupicchu.png" server="ftp.fatcow.com" local="132819368980000000" remote="132840604200000000" Dst="0" />
<file name="mercy03.jpg" server="ftp.fatcow.com" local="132819368980000000" remote="132840604200000000" Dst="0" />
<file name="payment.jpg" server="ftp.fatcow.com" local="132819368980000000" remote="132840604200000000" Dst="0" />
<file name="pin-bg.png" server="ftp.fatcow.com" local="132819369000000000" remote="132840604200000000" Dst="0" />
<file name="artesania-peru.jpg" server="ftp.fatcow.com" local="132830413440000000" remote="132840603600000000" Dst="0" />
<file name="extreme-tours-andea-exclusive.jpg" server="ftp.fatcow.com" local="132839204740000000" remote="132840603600000000" Dst="0" />
<file name="Extreme.tours-andean-exclusive.png" server="ftp.fatcow.com" local="132839205540000000" remote="132840603600000000" Dst="0" />
<file name="Transporte-andean-exclusive.png" server="ftp.fatcow.com" local="132839198460000000" remote="132840605400000000" Dst="0" />
<file name="climbing-peru-adventures-andean.jpg" server="ftp.fatcow.com" local="132841707370878505" remote="132841712400000000" Dst="0" />
<file name="hermoso-peru.jpg" server="ftp.fatcow.com" local="132852933114499596" remote="132852934800000000" Dst="0" />
<file name="blog-hiking-peru.jpg" server="157.245.81.162" local="132819368800000000" remote="132962554800000000" Dst="0" />
<file name="artesania-peru.jpg" server="157.245.81.162" local="132830413440000000" remote="132962554800000000" Dst="0" />
<file name="book AET.jpg" server="157.245.81.162" local="132819368820000000" remote="132962554800000000" Dst="0" />
<file name="book-your-destination-to-peru.jpg" server="157.245.81.162" local="132819368820000000" remote="132962554800000000" Dst="0" />
<file name="CHINCHERO.jpg" server="157.245.81.162" local="132819368780000000" remote="132962554800000000" Dst="0" />
<file name="chincheros.jpg" server="157.245.81.162" local="132819368840000000" remote="132962554800000000" Dst="0" />
<file name="climbing-peru-adventures-andean.jpg" server="157.245.81.162" local="132841707370878505" remote="132962554800000000" Dst="0" />
<file name="condor.png" server="157.245.81.162" local="132819368840000000" remote="132962554800000000" Dst="0" />
<file name="cusco-de-noche.jpg" server="157.245.81.162" local="132819368840000000" remote="132962554800000000" Dst="0" />
<file name="extreme-tours-andea-exclusive.jpg" server="157.245.81.162" local="132839204740000000" remote="132962554800000000" Dst="0" />
<file name="Extreme.tours-andean-exclusive.png" server="157.245.81.162" local="132839205540000000" remote="132962554800000000" Dst="0" />
<file name="hermoso-peru.jpg" server="157.245.81.162" local="132852933114499596" remote="132962554800000000" Dst="0" />
<file name="Humantay.jpg" server="157.245.81.162" local="132819368780000000" remote="132962554800000000" Dst="0" />
<file name="faqs.jpg" server="157.245.81.162" local="132819368860000000" remote="132962554800000000" Dst="0" />
<file name="ingles.png" server="157.245.81.162" local="132819368920000000" remote="132962555400000000" Dst="0" />
<file name="line.png" server="157.245.81.162" local="132901951887427322" remote="132962555400000000" Dst="0" />
<file name="llama2.jpg" server="157.245.81.162" local="132819368940000000" remote="132962555400000000" Dst="0" />
<file name="logodjm.png" server="157.245.81.162" local="132820114340000000" remote="132962555400000000" Dst="0" />
<file name="logoico.png" server="157.245.81.162" local="132819368940000000" remote="132962555400000000" Dst="0" />
<file name="llamas.jpg" server="157.245.81.162" local="132819368940000000" remote="132962555400000000" Dst="0" />
<file name="machupicchu.webp" server="157.245.81.162" local="132919378731898570" remote="132962555400000000" Dst="0" />
<file name="machupicchu.png" server="157.245.81.162" local="132819368980000000" remote="132962555400000000" Dst="0" />
<file name="Machu-Picchu-exclusive.jpg" server="157.245.81.162" local="132819368840000000" remote="132962555400000000" Dst="0" />
<file name="mercy03.jpg" server="157.245.81.162" local="132819368980000000" remote="132962555400000000" Dst="0" />
<file name="opiniones.png" server="157.245.81.162" local="132819368960000000" remote="132962555400000000" Dst="0" />
<file name="otorongo-jaguars.jpg" server="157.245.81.162" local="132819368980000000" remote="132962555400000000" Dst="0" />
<file name="payment.jpg" server="157.245.81.162" local="132819368980000000" remote="132962555400000000" Dst="0" />
<file name="pin-bg.png" server="157.245.81.162" local="132819369000000000" remote="132962555400000000" Dst="0" />
<file name="tour-guide-peru-tours.webp" server="157.245.81.162" local="132919384196020013" remote="132962566800000000" Dst="0" />
<file name="Transporte-andean-exclusive.png" server="157.245.81.162" local="132839198460000000" remote="132962566800000000" Dst="0" />
<file name="traduccion-es.png" server="216.246.47.134" local="133753772869447126" remote="133704517800000000" Dst="0" />
<file name="aatc.png" server="216.246.47.134" local="133753772228799216" remote="133704771000000000" Dst="0" />
<file name="aptae.png" server="216.246.47.134" local="133753772234637817" remote="133704771000000000" Dst="0" />
<file name="artesania-peru.jpg" server="216.246.47.134" local="133753772242213423" remote="133701182400000000" Dst="0" />
<file name="blog-hiking-peru.jpg" server="216.246.47.134" local="133753772265422607" remote="133701182400000000" Dst="0" />
<file name="book-your-destination-to-peru.jpg" server="216.246.47.134" local="133753772270288954" remote="133701182400000000" Dst="0" />
<file name="cartuc.png" server="216.246.47.134" local="133753772274861974" remote="133704771000000000" Dst="0" />
<file name="book AET.jpg" server="216.246.47.134" local="133753772270321341" remote="133701182400000000" Dst="0" />
<file name="CHINCHERO.jpg" server="216.246.47.134" local="133753772190433118" remote="133701182400000000" Dst="0" />
<file name="codigoesssna.png" server="216.246.47.134" local="133753772307440551" remote="133704771000000000" Dst="0" />
<file name="chincheros.jpg" server="216.246.47.134" local="133753772303733008" remote="133701182400000000" Dst="0" />
<file name="climbing-peru-adventures-andean.jpg" server="216.246.47.134" local="133753772307743185" remote="133701182400000000" Dst="0" />
<file name="cusco-de-noche.jpg" server="216.246.47.134" local="133753772317159881" remote="133701182400000000" Dst="0" />
<file name="condor.png" server="216.246.47.134" local="133753772318201706" remote="133701182400000000" Dst="0" />
<file name="espaдa.png" server="216.246.47.134" local="133753772720618391" remote="133701182400000000" Dst="0" />
<file name="extreme-tours-andea-exclusive.jpg" server="216.246.47.134" local="133753772725171251" remote="133701182400000000" Dst="0" />
<file name="Extreme.tours-andean-exclusive.png" server="216.246.47.134" local="133753772188393931" remote="133701182400000000" Dst="0" />
<file name="GERCETUR.png" server="216.246.47.134" local="133753772202648986" remote="133704771000000000" Dst="0" />
<file name="hermoso-peru.jpg" server="216.246.47.134" local="133753772755878238" remote="133701182400000000" Dst="0" />
<file name="faqs.jpg" server="216.246.47.134" local="133753772732643806" remote="133701182400000000" Dst="0" />
<file name="Humantay.jpg" server="216.246.47.134" local="133753772204089974" remote="133701182400000000" Dst="0" />
<file name="ingles.png" server="216.246.47.134" local="133753772760616889" remote="133701182400000000" Dst="0" />
<file name="line.png" server="216.246.47.134" local="133753772761975068" remote="133701182400000000" Dst="0" />
<file name="llama2.jpg" server="216.246.47.134" local="133753772767163687" remote="133701182400000000" Dst="0" />
<file name="logo-pachatusan-trek.png" server="216.246.47.134" local="133753772772972105" remote="133701186600000000" Dst="0" />
<file name="llamas.jpg" server="216.246.47.134" local="133753772776535681" remote="133701182400000000" Dst="0" />
<file name="logodjm.png" server="216.246.47.134" local="133753772779769395" remote="133701182400000000" Dst="0" />
<file name="logoico.png" server="216.246.47.134" local="133753772781501747" remote="133701182400000000" Dst="0" />
<file name="Machu-Picchu-exclusive.jpg" server="216.246.47.134" local="133753772219350470" remote="133701182400000000" Dst="0" />
<file name="machupicchu.png" server="216.246.47.134" local="133753772794905564" remote="133701182400000000" Dst="0" />
<file name="machupicchu.webp" server="216.246.47.134" local="133753772798668875" remote="133701182400000000" Dst="0" />
<file name="marca-peru.png" server="216.246.47.134" local="133753772788749782" remote="133704771600000000" Dst="0" />
<file name="mincetur.png" server="216.246.47.134" local="133753772805151303" remote="133704771000000000" Dst="0" />
<file name="opiniones.png" server="216.246.47.134" local="133753772808000838" remote="133701182400000000" Dst="0" />
<file name="mercy03.jpg" server="216.246.47.134" local="133753772812846999" remote="133701182400000000" Dst="0" />
<file name="otorongo-jaguars.jpg" server="216.246.47.134" local="133753772812968070" remote="133701182400000000" Dst="0" />
<file name="pachatusan-icon.png" server="216.246.47.134" local="133753772814286653" remote="133701187800000000" Dst="0" />
<file name="payment.jpg" server="216.246.47.134" local="133753772820654269" remote="133701182400000000" Dst="0" />
<file name="pfp.png" server="216.246.47.134" local="133753772822175910" remote="133704771600000000" Dst="0" />
<file name="pin-bg.png" server="216.246.47.134" local="133753772820664215" remote="133701182400000000" Dst="0" />
<file name="sernanp.png" server="216.246.47.134" local="133753772827120274" remote="133704771600000000" Dst="0" />
<file name="tour-guide-peru-tours.webp" server="216.246.47.134" local="133753772863038496" remote="133701182400000000" Dst="0" />
<file name="TourCert.png" server="216.246.47.134" local="133753772226587222" remote="133704765000000000" Dst="0" />
<file name="Transporte-andean-exclusive.png" server="216.246.47.134" local="133753772225108418" remote="133701182400000000" Dst="0" />
<file name="espana.png" server="216.246.47.134" local="133753772715240306" remote="133701182400000000" Dst="0" />
<file name="andean_exclusive_tours_slide2.jpg" server="216.246.47.134" local="133753772235210343" remote="133701182400000000" Dst="0" />
<file name="banner-seguridad.png" server="216.246.47.134" local="133753772243111186" remote="133701182400000000" Dst="0" />
<file name="logo-Pachatusan-Trek-blanco.png" server="216.246.47.134" local="133758197572742888" remote="133758199200000000" Dst="0" />
<file name="Extreme.tours-andean-exclusive.png" server="ftp.pachatusantrek.com" local="133824825436922235" remote="133753951800000000" Dst="0" />
<file name="CHINCHERO.jpg" server="ftp.pachatusantrek.com" local="133824825445404528" remote="133753951800000000" Dst="0" />
<file name="GERCETUR.png" server="ftp.pachatusantrek.com" local="133824826475117554" remote="133753951800000000" Dst="0" />
<file name="Humantay.jpg" server="ftp.pachatusantrek.com" local="133824826481185989" remote="133753951800000000" Dst="0" />
<file name="Logo-blanco-andean.png" server="ftp.pachatusantrek.com" local="133824826493691688" remote="133753951800000000" Dst="0" />
<file name="Machu-Picchu-exclusive.jpg" server="ftp.pachatusantrek.com" local="133824826527841486" remote="133753951800000000" Dst="0" />
<file name="TourCert.png" server="ftp.pachatusantrek.com" local="133824827474482365" remote="133753951800000000" Dst="0" />
<file name="Transporte-andean-exclusive.png" server="ftp.pachatusantrek.com" local="133824827479286855" remote="133753951800000000" Dst="0" />
<file name="andean_exclusive_tours_slide2.jpg" server="ftp.pachatusantrek.com" local="133824827486138168" remote="133753951800000000" Dst="0" />
<file name="aptae.png" server="ftp.pachatusantrek.com" local="133824827488741715" remote="133753951800000000" Dst="0" />
<file name="banner-seguridad.png" server="ftp.pachatusantrek.com" local="133824827495460662" remote="133753951800000000" Dst="0" />
<file name="aatc.png" server="ftp.pachatusantrek.com" local="133824827497173411" remote="133753951800000000" Dst="0" />
<file name="artesania-peru.jpg" server="ftp.pachatusantrek.com" local="133824827516803010" remote="133753951800000000" Dst="0" />
<file name="book-your-destination-to-peru.jpg" server="ftp.pachatusantrek.com" local="133824828571594221" remote="133753951800000000" Dst="0" />
<file name="blog-hiking-peru.jpg" server="ftp.pachatusantrek.com" local="133824828575678436" remote="133753951800000000" Dst="0" />
<file name="cartuc.png" server="ftp.pachatusantrek.com" local="133824828585753327" remote="133753951800000000" Dst="0" />
<file name="book AET.jpg" server="ftp.pachatusantrek.com" local="133824828642984886" remote="133753951800000000" Dst="0" />
<file name="chincheros.jpg" server="ftp.pachatusantrek.com" local="133824828731675091" remote="133753951800000000" Dst="0" />
<file name="codigoesssna.png" server="ftp.pachatusantrek.com" local="133824828740071695" remote="133753951800000000" Dst="0" />
<file name="condor.png" server="ftp.pachatusantrek.com" local="133824828783632680" remote="133753951800000000" Dst="0" />
<file name="cusco-de-noche.jpg" server="ftp.pachatusantrek.com" local="133824828798882915" remote="133753951800000000" Dst="0" />
<file name="climbing-peru-adventures-andean.jpg" server="ftp.pachatusantrek.com" local="133824828804851030" remote="133753951800000000" Dst="0" />
<file name="espana.png" server="ftp.pachatusantrek.com" local="133824829717420311" remote="133753952400000000" Dst="0" />
<file name="espaдa.png" server="ftp.pachatusantrek.com" local="133824829722714771" remote="133753952400000000" Dst="0" />
<file name="extreme-tours-andea-exclusive.jpg" server="ftp.pachatusantrek.com" local="133824829735758056" remote="133753952400000000" Dst="0" />
<file name="faqs.jpg" server="ftp.pachatusantrek.com" local="133824829749910047" remote="133753952400000000" Dst="0" />
<file name="hermoso-peru.jpg" server="ftp.pachatusantrek.com" local="133824839327895494" remote="133753952400000000" Dst="0" />
<file name="ingles.png" server="ftp.pachatusantrek.com" local="133824839481285726" remote="133753952400000000" Dst="0" />
<file name="line.png" server="ftp.pachatusantrek.com" local="133824839484311404" remote="133753952400000000" Dst="0" />
<file name="logo-Pachatusan-Trek-blanco.png" server="ftp.pachatusantrek.com" local="133824839494471925" remote="133758377400000000" Dst="0" />
<file name="llama2.jpg" server="ftp.pachatusantrek.com" local="133824839495593535" remote="133753952400000000" Dst="0" />
<file name="logo2.png" server="ftp.pachatusantrek.com" local="133824839500444118" remote="133753952400000000" Dst="0" />
<file name="logodjm.png" server="ftp.pachatusantrek.com" local="133824839505751931" remote="133753952400000000" Dst="0" />
<file name="logo-pachatusan-trek.png" server="ftp.pachatusantrek.com" local="133824839508246846" remote="133753952400000000" Dst="0" />
<file name="logoico.png" server="ftp.pachatusantrek.com" local="133824839510674055" remote="133753952400000000" Dst="0" />
<file name="llamas.jpg" server="ftp.pachatusantrek.com" local="133824839510945030" remote="133753952400000000" Dst="0" />
<file name="machupicchu.webp" server="ftp.pachatusantrek.com" local="133824839578549099" remote="133753952400000000" Dst="0" />
<file name="machupicchu.png" server="ftp.pachatusantrek.com" local="133824839580777051" remote="133753952400000000" Dst="0" />
<file name="marca-peru.png" server="ftp.pachatusantrek.com" local="133824839746078153" remote="133753952400000000" Dst="0" />
<file name="mincetur.png" server="ftp.pachatusantrek.com" local="133824839758538180" remote="133753952400000000" Dst="0" />
<file name="otorongo-jaguars.jpg" server="ftp.pachatusantrek.com" local="133824839764558889" remote="133753952400000000" Dst="0" />
<file name="pachatusan-icon.png" server="ftp.pachatusantrek.com" local="133824839769818407" remote="133753952400000000" Dst="0" />
<file name="opiniones.png" server="ftp.pachatusantrek.com" local="133824839770377126" remote="133753952400000000" Dst="0" />
<file name="mercy03.jpg" server="ftp.pachatusantrek.com" local="133824839778377442" remote="133753952400000000" Dst="0" />
<file name="pfp.png" server="ftp.pachatusantrek.com" local="133824839781036612" remote="133753952400000000" Dst="0" />
<file name="pin-bg.png" server="ftp.pachatusantrek.com" local="133824839784485398" remote="133753952400000000" Dst="0" />
<file name="payment.jpg" server="ftp.pachatusantrek.com" local="133824839785743547" remote="133753952400000000" Dst="0" />
<file name="sernanp.png" server="ftp.pachatusantrek.com" local="133824839905014327" remote="133753952400000000" Dst="0" />
<file name="tour-guide-peru-tours.webp" server="ftp.pachatusantrek.com" local="133824840895649763" remote="133753952400000000" Dst="0" />
<file name="traduccion-es.png" server="ftp.pachatusantrek.com" local="133824841252219570" remote="133753952400000000" Dst="0" />
</dwsync>